<?xml version="1.0" encoding="UTF-8"?>
<document reference="suspicious-document01903.txt">
  <feature name="about" authors="Waller, Mary Ella" title="Flamsted quarries" lang="en" />
  <feature name="md5Hash" value="4ab37c20e8e4b0914a712ff334d414d9" />
  <feature name="plagiarism" type="artificial" obfuscation="none" this_language="en" this_offset="11664" this_length="1466" />
  <feature name="plagiarism" type="artificial" obfuscation="none" this_language="en" this_offset="43244" this_length="691" />
  <feature name="plagiarism" type="artificial" obfuscation="none" this_language="en" this_offset="60545" this_length="4999" />
  <feature name="plagiarism" type="artificial" obfuscation="none" this_language="en" this_offset="210243" this_length="2963" />
  <feature name="plagiarism" type="artificial" obfuscation="none" this_language="en" this_offset="270888" this_length="485" />
  <feature name="plagiarism" type="artificial" obfuscation="none" this_language="en" this_offset="282251" this_length="270" />
  <feature name="plagiarism" type="artificial" obfuscation="none" this_language="en" this_offset="290963" this_length="452" />
  <feature name="plagiarism" type="artificial" obfuscation="none" this_language="en" this_offset="299886" this_length="770" />
  <feature name="plagiarism" type="artificial" obfuscation="none" this_language="en" this_offset="320929" this_length="455" />
  <feature name="plagiarism" type="artificial" obfuscation="none" this_language="en" this_offset="330762" this_length="225" />
</document>

