<?xml version="1.0" encoding="UTF-8"?>
<document reference="suspicious-document00802.txt">
  <feature name="about" authors="Churchill, Winston" title="Mr. Crewe's Career — Volume 3" lang="en" />
  <feature name="md5Hash" value="173c350c05598a30a25e9efd9660b2c0" />
  <feature name="plagiarism" type="artificial" obfuscation="none" this_language="en" this_offset="26122" this_length="5035" />
  <feature name="plagiarism" type="artificial" obfuscation="none" this_language="en" this_offset="69662" this_length="269" />
  <feature name="plagiarism" type="artificial" obfuscation="none" this_language="en" this_offset="80449" this_length="4707" />
  <feature name="plagiarism" type="artificial" obfuscation="none" this_language="en" this_offset="142339" this_length="2277" />
  <feature name="plagiarism" type="artificial" obfuscation="none" this_language="en" this_offset="167734" this_length="5069" />
  <feature name="plagiarism" type="artificial" obfuscation="none" this_language="en" this_offset="249221" this_length="3255" />
  <feature name="plagiarism" type="artificial" obfuscation="none" this_language="en" this_offset="274245" this_length="470" />
  <feature name="plagiarism" type="artificial" obfuscation="none" this_language="en" this_offset="281060" this_length="244" />
</document>

