<?xml version="1.0" encoding="UTF-8"?>
<document reference="suspicious-document01508.txt">
  <feature name="about" authors="Doyle, Arthur Conan, Sir" title="Tales of Terror and Mystery" lang="en" />
  <feature name="md5Hash" value="37e8c0825f29f4ac12ad7d747b918c33" />
  <feature name="plagiarism" type="artificial" obfuscation="none" this_language="en" this_offset="44764" this_length="16922" />
  <feature name="plagiarism" type="artificial" obfuscation="none" this_language="en" this_offset="209368" this_length="3916" />
  <feature name="plagiarism" type="artificial" obfuscation="none" this_language="en" this_offset="247305" this_length="481" />
  <feature name="plagiarism" type="artificial" obfuscation="none" this_language="en" this_offset="272719" this_length="2527" />
  <feature name="plagiarism" type="artificial" obfuscation="none" this_language="en" this_offset="288088" this_length="3268" />
  <feature name="plagiarism" type="artificial" obfuscation="none" this_language="en" this_offset="335493" this_length="2899" />
  <feature name="plagiarism" type="artificial" obfuscation="none" this_language="en" this_offset="351107" this_length="710" />
  <feature name="plagiarism" type="artificial" obfuscation="none" this_language="en" this_offset="361049" this_length="235" />
  <feature name="plagiarism" type="artificial" obfuscation="none" this_language="en" this_offset="363277" this_length="240" />
  <feature name="plagiarism" type="artificial" obfuscation="none" this_language="en" this_offset="368983" this_length="760" />
</document>

